semaphore_api/__init__.py
semaphore_api/api_client.py
semaphore_api/api_response.py
semaphore_api/configuration.py
semaphore_api/exceptions.py
semaphore_api/py.typed
semaphore_api/rest.py
semaphore_api/api/__init__.py
semaphore_api/api/authentication_api.py
semaphore_api/api/default_api.py
semaphore_api/api/integration_api.py
semaphore_api/api/project_api.py
semaphore_api/api/projects_api.py
semaphore_api/api/schedule_api.py
semaphore_api/api/user_api.py
semaphore_api/models/__init__.py
semaphore_api/models/access_key.py
semaphore_api/models/access_key_request.py
semaphore_api/models/access_key_request_login_password.py
semaphore_api/models/access_key_request_ssh.py
semaphore_api/models/api_token.py
semaphore_api/models/environment.py
semaphore_api/models/environment_request.py
semaphore_api/models/event.py
semaphore_api/models/info_type.py
semaphore_api/models/info_type_update.py
semaphore_api/models/integration.py
semaphore_api/models/integration_extract_value.py
semaphore_api/models/integration_extract_value_request.py
semaphore_api/models/integration_matcher.py
semaphore_api/models/integration_matcher_request.py
semaphore_api/models/integration_request.py
semaphore_api/models/inventory.py
semaphore_api/models/inventory_request.py
semaphore_api/models/login.py
semaphore_api/models/login_metadata.py
semaphore_api/models/login_metadata_oidc_providers_inner.py
semaphore_api/models/project.py
semaphore_api/models/project_backup.py
semaphore_api/models/project_backup_environments_inner.py
semaphore_api/models/project_backup_inventories_inner.py
semaphore_api/models/project_backup_keys_inner.py
semaphore_api/models/project_backup_meta.py
semaphore_api/models/project_backup_repositories_inner.py
semaphore_api/models/project_backup_templates_inner.py
semaphore_api/models/project_backup_views_inner.py
semaphore_api/models/project_project_id_put_request.py
semaphore_api/models/project_project_id_role_get200_response.py
semaphore_api-2.10.7.dist-info/LICENSE
semaphore_api-2.10.7.dist-info/METADATA
semaphore_api-2.10.7.dist-info/WHEEL
semaphore_api-2.10.7.dist-info/top_level.txt
semaphore_api-2.10.7.dist-info/RECORD
